<?xml version="1.0" encoding="UTF-8"?>
<!DOCTYPE hibernate-mapping PUBLIC "-//Hibernate/Hibernate Mapping DTD 3.0//EN"
"http://hibernate.sourceforge.net/hibernate-mapping-3.0.dtd">
<hibernate-mapping>
	<class name="com.unla.datos.TipoHabitacion" table="tipohabitacion">
		<id column="idTipoHabitacion" name="idTipoHabitacion">
			<generator class="identity" />
		</id>
		<property column="descripcion" name="descripcion" type="string" />
   		<!-- 
   		<set name="habitaciones" table="habitacion" order-by="idTipoHabitacion asc" inverse="true" lazy="true" fetch="select">
		<key column="idTipoHabitacion" not-null="true" />
		<one-to-many class="com.unla.datos.Habitacion" />
		</set>
   	 	-->
	</class>
</hibernate-mapping>